{
 "text": "Imasmiñca pana veyyākaraṇasmiṃ bhaññamāne āyasmato koṇḍaññassa virajaṃ vītamalaṃ dhammacakkhuṃ udapādi yaṃ kiñci samudayadhammaṃ sabbaṃ taṃ nirodhadhamma nti",
 "edit": "Imasmiñca pana veyyākaraṇasmiṃ bhaññamāne āyasmato koṇḍaññassa virajaṃ vītamalaṃ dhammacakkhuṃ udapādi – yaṃ kiñci samudayadhammaṃ sabbaṃ taṃ nirodhadhamma nti",
 "translations": [
  {
   "variant": "PTR",
   "transtext": "While this explanation was being said, the Venerable Koṇḍañña's Dhamma eye arose immaculately thus, \"Whichever [is normally] arising nature, that all [is normally] ceasing nature.\""
  }
 ]
}